haystack_integrations/components/retrievers/py.typed
haystack_integrations/components/retrievers/elasticsearch/__init__.py
haystack_integrations/components/retrievers/elasticsearch/bm25_retriever.py
haystack_integrations/components/retrievers/elasticsearch/embedding_retriever.py
haystack_integrations/document_stores/py.typed
haystack_integrations/document_stores/elasticsearch/__init__.py
haystack_integrations/document_stores/elasticsearch/document_store.py
haystack_integrations/document_stores/elasticsearch/filters.py
elasticsearch_haystack-5.1.0.dist-info/METADATA
elasticsearch_haystack-5.1.0.dist-info/WHEEL
elasticsearch_haystack-5.1.0.dist-info/licenses/LICENSE
elasticsearch_haystack-5.1.0.dist-info/RECORD
